.installed.cfg
.mr.developer.cfg
CHANGES.rst
CONTRIBUTORS.rst
MANIFEST.in
README.rst
buildout.cfg
picked-versions.cfg
setup.py
travis.cfg
src/collective/__init__.py
src/collective/__init__.pyc
src/collective.awstats_hitcounter.egg-info/PKG-INFO
src/collective.awstats_hitcounter.egg-info/SOURCES.txt
src/collective.awstats_hitcounter.egg-info/dependency_links.txt
src/collective.awstats_hitcounter.egg-info/entry_points.txt
src/collective.awstats_hitcounter.egg-info/namespace_packages.txt
src/collective.awstats_hitcounter.egg-info/not-zip-safe
src/collective.awstats_hitcounter.egg-info/requires.txt
src/collective.awstats_hitcounter.egg-info/top_level.txt
src/collective/awstats_hitcounter/__init__.py
src/collective/awstats_hitcounter/__init__.pyc
src/collective/awstats_hitcounter/configure.zcml
src/collective/awstats_hitcounter/interfaces.py
src/collective/awstats_hitcounter/interfaces.pyc
src/collective/awstats_hitcounter/setuphandlers.py
src/collective/awstats_hitcounter/setuphandlers.pyc
src/collective/awstats_hitcounter/testing.py
src/collective/awstats_hitcounter/upgrades.py
src/collective/awstats_hitcounter/upgrades.pyc
src/collective/awstats_hitcounter/upgrades.zcml
src/collective/awstats_hitcounter/browser/__init__.py
src/collective/awstats_hitcounter/browser/__init__.pyc
src/collective/awstats_hitcounter/browser/configure.zcml
src/collective/awstats_hitcounter/browser/popular_content_view.pt
src/collective/awstats_hitcounter/browser/utils.py
src/collective/awstats_hitcounter/browser/utils.pyc
src/collective/awstats_hitcounter/browser/views.py
src/collective/awstats_hitcounter/browser/views.pyc
src/collective/awstats_hitcounter/browser/static/.gitkeep
src/collective/awstats_hitcounter/browser/static/app.js
src/collective/awstats_hitcounter/browser/static/awstats-icon.png
src/collective/awstats_hitcounter/locales/collective.awstats_hitcounter.pot
src/collective/awstats_hitcounter/locales/update.sh
src/collective/awstats_hitcounter/portlet/__init__.py
src/collective/awstats_hitcounter/portlet/__init__.pyc
src/collective/awstats_hitcounter/portlet/configure.zcml
src/collective/awstats_hitcounter/portlet/popularcontentportlet.pt
src/collective/awstats_hitcounter/portlet/portlets.py
src/collective/awstats_hitcounter/portlet/portlets.pyc
src/collective/awstats_hitcounter/portlet/z3cformhelper.py
src/collective/awstats_hitcounter/portlet/z3cformhelper.pyc
src/collective/awstats_hitcounter/portlet/static/style.css
