Metadata-Version: 1.1
Name: collective.awstats-hitcounter
Version: 0.1.6.1
Summary: Grabs hit counts from awstats and returns as json formatted data
Home-page: http://pypi.python.org/pypi/collective.awstats_hitcounter
Author: David Bain
Author-email: david@alteroo.com
License: GPL
Keywords: Python Plone
Platform: UNKNOWN
Classifier: Environment :: Web Environment
Classifier: Framework :: Plone
Classifier: Programming Language :: Python
Classifier: Programming Language :: Python :: 2.7
Classifier: Programming Language :: Python :: 2.6
